{"cid": 60550243, "titleFormat": "\u7b2c1\u8bdd", "longTitle": "\u98ce\u96be\u6b62", "ep_id": 253576, "v_split_list": ["https://112-13-78-5.ksyungslb.com/upos-sz-mirrorks32u.acgvideo.com/upgcxcode/43/02/60550243/60550243-1-80.flv?deadline=1462165219&gen=playurl&nbs=1&oi=1879473321&os=ks3u&platform=pc&trid=80a358d94bc442babc00f32db8ced2e5&uipk=5&upsig=988ad3ae4a680b41baccaafcf80bd2a8&uparams=deadline,gen,nbs,oi,os,platform,trid,uipk&mid=165584183&ksy_gslb_referer=https%3A%2F%2Fwww.bilibili.com%2Fvideo%2Fav14063582%2F%3Fspm_id_from%3D333.788.videocard.1"]}
{"cid": 61525848, "titleFormat": "\u7b2c2\u8bdd", "longTitle": "\u6697\u6f6e\u6d8c", "ep_id": 253577, "v_split_list": ["https://112-13-78-5.ksyungslb.com/upos-sz-mirrorks32u.acgvideo.com/upgcxcode/48/58/61525848/61525848-1-80.flv?deadline=1462165219&gen=playurl&nbs=1&oi=1879473321&os=ks3u&platform=pc&trid=80a358d94bc442babc00f32db8ced2e5&uipk=5&upsig=988ad3ae4a680b41baccaafcf80bd2a8&uparams=deadline,gen,nbs,oi,os,platform,trid,uipk&mid=165584183&ksy_gslb_referer=https%3A%2F%2Fwww.bilibili.com%2Fvideo%2Fav14063582%2F%3Fspm_id_from%3D333.788.videocard.1"]}
{"cid": 61194562, "titleFormat": "\u7b2c3\u8bdd", "longTitle": "\u674e\u5927\u767d", "ep_id": 253911, "v_split_list": ["https://112-13-78-5.ksyungslb.com/upos-sz-mirrorks32u.acgvideo.com/upgcxcode/62/45/61194562/61194562-1-80.flv?deadline=1462165219&gen=playurl&nbs=1&oi=1879473321&os=ks3u&platform=pc&trid=80a358d94bc442babc00f32db8ced2e5&uipk=5&upsig=988ad3ae4a680b41baccaafcf80bd2a8&uparams=deadline,gen,nbs,oi,os,platform,trid,uipk&mid=165584183&ksy_gslb_referer=https%3A%2F%2Fwww.bilibili.com%2Fvideo%2Fav14063582%2F%3Fspm_id_from%3D333.788.videocard.1"]}
{"cid": 66689102, "titleFormat": "\u7b2c4\u8bdd", "longTitle": "\u5c24\u5ddd", "ep_id": 253912, "v_split_list": ["https://112-13-78-5.ksyungslb.com/upos-sz-mirrorks32u.acgvideo.com/upgcxcode/02/91/66689102/66689102-1-80.flv?deadline=1462165219&gen=playurl&nbs=1&oi=1879473321&os=ks3u&platform=pc&trid=80a358d94bc442babc00f32db8ced2e5&uipk=5&upsig=988ad3ae4a680b41baccaafcf80bd2a8&uparams=deadline,gen,nbs,oi,os,platform,trid,uipk&mid=165584183&ksy_gslb_referer=https%3A%2F%2Fwww.bilibili.com%2Fvideo%2Fav14063582%2F%3Fspm_id_from%3D333.788.videocard.1"]}
{"cid": 62983639, "titleFormat": "\u7b2c5\u8bdd", "longTitle": "\u76f8\u4f9d\u4e3a\u547d", "ep_id": 254473, "v_split_list": ["https://112-13-78-5.ksyungslb.com/upos-sz-mirrorks32u.acgvideo.com/upgcxcode/39/36/62983639/62983639-1-80.flv?deadline=1462165219&gen=playurl&nbs=1&oi=1879473321&os=ks3u&platform=pc&trid=80a358d94bc442babc00f32db8ced2e5&uipk=5&upsig=988ad3ae4a680b41baccaafcf80bd2a8&uparams=deadline,gen,nbs,oi,os,platform,trid,uipk&mid=165584183&ksy_gslb_referer=https%3A%2F%2Fwww.bilibili.com%2Fvideo%2Fav14063582%2F%3Fspm_id_from%3D333.788.videocard.1"]}
{"cid": 63982199, "titleFormat": "\u7b2c6\u8bdd", "longTitle": "\u805a\u5408\u795e\u79bb", "ep_id": 255130, "v_split_list": ["https://112-13-78-5.ksyungslb.com/upos-sz-mirrorks32u.acgvideo.com/upgcxcode/99/21/63982199/63982199-1-80.flv?deadline=1462165219&gen=playurl&nbs=1&oi=1879473321&os=ks3u&platform=pc&trid=80a358d94bc442babc00f32db8ced2e5&uipk=5&upsig=988ad3ae4a680b41baccaafcf80bd2a8&uparams=deadline,gen,nbs,oi,os,platform,trid,uipk&mid=165584183&ksy_gslb_referer=https%3A%2F%2Fwww.bilibili.com%2Fvideo%2Fav14063582%2F%3Fspm_id_from%3D333.788.videocard.1"]}
{"cid": 64777453, "titleFormat": "\u7b2c7\u8bdd", "longTitle": "\u7434\u5934\u7b1b\u5c3e", "ep_id": 255131, "v_split_list": ["https://112-13-78-5.ksyungslb.com/upos-sz-mirrorks32u.acgvideo.com/upgcxcode/53/74/64777453/64777453-1-80.flv?deadline=1462165219&gen=playurl&nbs=1&oi=1879473321&os=ks3u&platform=pc&trid=80a358d94bc442babc00f32db8ced2e5&uipk=5&upsig=988ad3ae4a680b41baccaafcf80bd2a8&uparams=deadline,gen,nbs,oi,os,platform,trid,uipk&mid=165584183&ksy_gslb_referer=https%3A%2F%2Fwww.bilibili.com%2Fvideo%2Fav14063582%2F%3Fspm_id_from%3D333.788.videocard.1"]}
{"cid": 67599351, "titleFormat": "\u7b2c8\u8bdd", "longTitle": "\u5b9a\u98ce\u6ce2", "ep_id": 257441, "v_split_list": ["https://112-13-78-5.ksyungslb.com/upos-sz-mirrorks32u.acgvideo.com/upgcxcode/51/93/67599351/67599351-1-80.flv?deadline=1462165219&gen=playurl&nbs=1&oi=1879473321&os=ks3u&platform=pc&trid=80a358d94bc442babc00f32db8ced2e5&uipk=5&upsig=988ad3ae4a680b41baccaafcf80bd2a8&uparams=deadline,gen,nbs,oi,os,platform,trid,uipk&mid=165584183&ksy_gslb_referer=https%3A%2F%2Fwww.bilibili.com%2Fvideo%2Fav14063582%2F%3Fspm_id_from%3D333.788.videocard.1"]}
{"cid": 66662028, "titleFormat": "\u7b2c9\u8bdd", "longTitle": "\u8d1f\u8f7d\u800c\u884c", "ep_id": 258039, "v_split_list": ["https://112-13-78-5.ksyungslb.com/upos-sz-mirrorks32u.acgvideo.com/upgcxcode/28/20/66662028/66662028-1-80.flv?deadline=1462165219&gen=playurl&nbs=1&oi=1879473321&os=ks3u&platform=pc&trid=80a358d94bc442babc00f32db8ced2e5&uipk=5&upsig=988ad3ae4a680b41baccaafcf80bd2a8&uparams=deadline,gen,nbs,oi,os,platform,trid,uipk&mid=165584183&ksy_gslb_referer=https%3A%2F%2Fwww.bilibili.com%2Fvideo%2Fav14063582%2F%3Fspm_id_from%3D333.788.videocard.1"]}
{"cid": 67735515, "titleFormat": "\u7b2c10\u8bdd", "longTitle": "\u7965\u4e91\u5316\u96e8", "ep_id": 258330, "v_split_list": ["https://112-13-78-5.ksyungslb.com/upos-sz-mirrorks32u.acgvideo.com/upgcxcode/15/55/67735515/67735515-1-80.flv?deadline=1462165219&gen=playurl&nbs=1&oi=1879473321&os=ks3u&platform=pc&trid=80a358d94bc442babc00f32db8ced2e5&uipk=5&upsig=988ad3ae4a680b41baccaafcf80bd2a8&uparams=deadline,gen,nbs,oi,os,platform,trid,uipk&mid=165584183&ksy_gslb_referer=https%3A%2F%2Fwww.bilibili.com%2Fvideo%2Fav14063582%2F%3Fspm_id_from%3D333.788.videocard.1"]}
{"cid": 68537173, "titleFormat": "\u7b2c11\u8bdd", "longTitle": "\u91cd\u5c71\u8ff7\u96fe", "ep_id": 258700, "v_split_list": ["https://112-13-78-5.ksyungslb.com/upos-sz-mirrorks32u.acgvideo.com/upgcxcode/73/71/68537173/68537173-1-80.flv?deadline=1462165219&gen=playurl&nbs=1&oi=1879473321&os=ks3u&platform=pc&trid=80a358d94bc442babc00f32db8ced2e5&uipk=5&upsig=988ad3ae4a680b41baccaafcf80bd2a8&uparams=deadline,gen,nbs,oi,os,platform,trid,uipk&mid=165584183&ksy_gslb_referer=https%3A%2F%2Fwww.bilibili.com%2Fvideo%2Fav14063582%2F%3Fspm_id_from%3D333.788.videocard.1"]}
{"cid": 69065072, "titleFormat": "\u7b2c12\u8bdd", "longTitle": "\u62e8\u96fe\u89c1\u4e91", "ep_id": 259035, "v_split_list": ["https://112-13-78-5.ksyungslb.com/upos-sz-mirrorks32u.acgvideo.com/upgcxcode/72/50/69065072/69065072-1-80.flv?deadline=1462165219&gen=playurl&nbs=1&oi=1879473321&os=ks3u&platform=pc&trid=80a358d94bc442babc00f32db8ced2e5&uipk=5&upsig=988ad3ae4a680b41baccaafcf80bd2a8&uparams=deadline,gen,nbs,oi,os,platform,trid,uipk&mid=165584183&ksy_gslb_referer=https%3A%2F%2Fwww.bilibili.com%2Fvideo%2Fav14063582%2F%3Fspm_id_from%3D333.788.videocard.1"]}
{"cid": 70789908, "titleFormat": "\u7b2c13\u8bdd", "longTitle": "\u4faf\u537f", "ep_id": 260071, "v_split_list": ["https://112-13-78-5.ksyungslb.com/upos-sz-mirrorks32u.acgvideo.com/upgcxcode/08/99/70789908/70789908-1-80.flv?deadline=1462165219&gen=playurl&nbs=1&oi=1879473321&os=ks3u&platform=pc&trid=80a358d94bc442babc00f32db8ced2e5&uipk=5&upsig=988ad3ae4a680b41baccaafcf80bd2a8&uparams=deadline,gen,nbs,oi,os,platform,trid,uipk&mid=165584183&ksy_gslb_referer=https%3A%2F%2Fwww.bilibili.com%2Fvideo%2Fav14063582%2F%3Fspm_id_from%3D333.788.videocard.1"]}
{"cid": 71800517, "titleFormat": "\u7b2c14\u8bdd", "longTitle": "\u91cd\u9022", "ep_id": 260488, "v_split_list": ["https://112-13-78-5.ksyungslb.com/upos-sz-mirrorks32u.acgvideo.com/upgcxcode/17/05/71800517/71800517-1-80.flv?deadline=1462165219&gen=playurl&nbs=1&oi=1879473321&os=ks3u&platform=pc&trid=80a358d94bc442babc00f32db8ced2e5&uipk=5&upsig=988ad3ae4a680b41baccaafcf80bd2a8&uparams=deadline,gen,nbs,oi,os,platform,trid,uipk&mid=165584183&ksy_gslb_referer=https%3A%2F%2Fwww.bilibili.com%2Fvideo%2Fav14063582%2F%3Fspm_id_from%3D333.788.videocard.1"]}
{"cid": 72671458, "titleFormat": "\u7b2c15\u8bdd", "longTitle": "\u5018\u6765\u4e4b\u9047", "ep_id": 260845, "v_split_list": ["https://112-13-78-5.ksyungslb.com/upos-sz-mirrorks32u.acgvideo.com/upgcxcode/58/14/72671458/72671458-1-80.flv?deadline=1462165219&gen=playurl&nbs=1&oi=1879473321&os=ks3u&platform=pc&trid=80a358d94bc442babc00f32db8ced2e5&uipk=5&upsig=988ad3ae4a680b41baccaafcf80bd2a8&uparams=deadline,gen,nbs,oi,os,platform,trid,uipk&mid=165584183&ksy_gslb_referer=https%3A%2F%2Fwww.bilibili.com%2Fvideo%2Fav14063582%2F%3Fspm_id_from%3D333.788.videocard.1"]}
{"cid": 73826556, "titleFormat": "\u7b2c16\u8bdd", "longTitle": "\u771f\u76f8\u5927\u767d", "ep_id": 261420, "v_split_list": ["https://112-13-78-5.ksyungslb.com/upos-sz-mirrorks32u.acgvideo.com/upgcxcode/56/65/73826556/73826556-1-80.flv?deadline=1462165219&gen=playurl&nbs=1&oi=1879473321&os=ks3u&platform=pc&trid=80a358d94bc442babc00f32db8ced2e5&uipk=5&upsig=988ad3ae4a680b41baccaafcf80bd2a8&uparams=deadline,gen,nbs,oi,os,platform,trid,uipk&mid=165584183&ksy_gslb_referer=https%3A%2F%2Fwww.bilibili.com%2Fvideo%2Fav14063582%2F%3Fspm_id_from%3D333.788.videocard.1"]}
{"cid": 74294341, "titleFormat": "\u7b2c17\u8bdd", "longTitle": "\u7edd\u5730\u6c42\u751f", "ep_id": 261855, "v_split_list": ["https://112-13-78-5.ksyungslb.com/upos-sz-mirrorks32u.acgvideo.com/upgcxcode/41/43/74294341/74294341-1-80.flv?deadline=1462165219&gen=playurl&nbs=1&oi=1879473321&os=ks3u&platform=pc&trid=80a358d94bc442babc00f32db8ced2e5&uipk=5&upsig=988ad3ae4a680b41baccaafcf80bd2a8&uparams=deadline,gen,nbs,oi,os,platform,trid,uipk&mid=165584183&ksy_gslb_referer=https%3A%2F%2Fwww.bilibili.com%2Fvideo%2Fav14063582%2F%3Fspm_id_from%3D333.788.videocard.1"]}
{"cid": 75763626, "titleFormat": "\u7b2c18\u8bdd", "longTitle": "\u5f03\u8f66\u4fdd\u5e05", "ep_id": 261856, "v_split_list": ["https://112-13-78-5.ksyungslb.com/upos-sz-mirrorks32u.acgvideo.com/upgcxcode/26/36/75763626/75763626-1-80.flv?deadline=1462165219&gen=playurl&nbs=1&oi=1879473321&os=ks3u&platform=pc&trid=80a358d94bc442babc00f32db8ced2e5&uipk=5&upsig=988ad3ae4a680b41baccaafcf80bd2a8&uparams=deadline,gen,nbs,oi,os,platform,trid,uipk&mid=165584183&ksy_gslb_referer=https%3A%2F%2Fwww.bilibili.com%2Fvideo%2Fav14063582%2F%3Fspm_id_from%3D333.788.videocard.1"]}
{"cid": 77377700, "titleFormat": "\u7b2c19\u8bdd", "longTitle": "\u91d1\u8749\u8131\u58f3", "ep_id": 262540, "v_split_list": ["https://112-13-78-5.ksyungslb.com/upos-sz-mirrorks32u.acgvideo.com/upgcxcode/00/77/77377700/77377700-1-80.flv?deadline=1462165219&gen=playurl&nbs=1&oi=1879473321&os=ks3u&platform=pc&trid=80a358d94bc442babc00f32db8ced2e5&uipk=5&upsig=988ad3ae4a680b41baccaafcf80bd2a8&uparams=deadline,gen,nbs,oi,os,platform,trid,uipk&mid=165584183&ksy_gslb_referer=https%3A%2F%2Fwww.bilibili.com%2Fvideo%2Fav14063582%2F%3Fspm_id_from%3D333.788.videocard.1"]}
{"cid": 78527081, "titleFormat": "\u7b2c20\u8bdd", "longTitle": "\u8fdf\u8fdf\u543e\u884c", "ep_id": 262819, "v_split_list": ["https://112-13-78-5.ksyungslb.com/upos-sz-mirrorks32u.acgvideo.com/upgcxcode/81/70/78527081/78527081-1-80.flv?deadline=1462165219&gen=playurl&nbs=1&oi=1879473321&os=ks3u&platform=pc&trid=80a358d94bc442babc00f32db8ced2e5&uipk=5&upsig=988ad3ae4a680b41baccaafcf80bd2a8&uparams=deadline,gen,nbs,oi,os,platform,trid,uipk&mid=165584183&ksy_gslb_referer=https%3A%2F%2Fwww.bilibili.com%2Fvideo%2Fav14063582%2F%3Fspm_id_from%3D333.788.videocard.1"]}
{"cid": 83028636, "titleFormat": "\u7b2c21\u8bdd", "longTitle": "\u51b0\u89e3\u7684\u7834", "ep_id": 263423, "v_split_list": ["https://112-13-78-5.ksyungslb.com/upos-sz-mirrorks32u.acgvideo.com/upgcxcode/36/86/83028636/83028636-1-80.flv?deadline=1462165219&gen=playurl&nbs=1&oi=1879473321&os=ks3u&platform=pc&trid=80a358d94bc442babc00f32db8ced2e5&uipk=5&upsig=988ad3ae4a680b41baccaafcf80bd2a8&uparams=deadline,gen,nbs,oi,os,platform,trid,uipk&mid=165584183&ksy_gslb_referer=https%3A%2F%2Fwww.bilibili.com%2Fvideo%2Fav14063582%2F%3Fspm_id_from%3D333.788.videocard.1"]}
{"cid": 96971968, "titleFormat": "\u7b2c22\u8bdd", "longTitle": "\u5389\u5175\u79e3\u9a6c", "ep_id": 264445, "v_split_list": ["https://112-13-78-5.ksyungslb.com/upos-sz-mirrorks32u.acgvideo.com/upgcxcode/68/19/96971968/96971968-1-32.flv?deadline=1462165219&gen=playurl&nbs=1&oi=1879473321&os=ks3u&platform=pc&trid=80a358d94bc442babc00f32db8ced2e5&uipk=5&upsig=988ad3ae4a680b41baccaafcf80bd2a8&uparams=deadline,gen,nbs,oi,os,platform,trid,uipk&mid=165584183&ksy_gslb_referer=https%3A%2F%2Fwww.bilibili.com%2Fvideo%2Fav14063582%2F%3Fspm_id_from%3D333.788.videocard.1"]}
{"cid": 96972069, "titleFormat": "\u7b2c23\u8bdd", "longTitle": "\u710a\u9b43", "ep_id": 274514, "v_split_list": ["https://112-13-78-5.ksyungslb.com/upos-sz-mirrorks32u.acgvideo.com/upgcxcode/69/20/96972069/96972069-1-32.flv?deadline=1462165219&gen=playurl&nbs=1&oi=1879473321&os=ks3u&platform=pc&trid=80a358d94bc442babc00f32db8ced2e5&uipk=5&upsig=988ad3ae4a680b41baccaafcf80bd2a8&uparams=deadline,gen,nbs,oi,os,platform,trid,uipk&mid=165584183&ksy_gslb_referer=https%3A%2F%2Fwww.bilibili.com%2Fvideo%2Fav14063582%2F%3Fspm_id_from%3D333.788.videocard.1"]}
{"cid": 98055686, "titleFormat": "\u7b2c24\u8bdd", "longTitle": "\u6251\u6714\u8ff7\u79bb", "ep_id": 274515, "v_split_list": ["https://112-13-78-5.ksyungslb.com/upos-sz-mirrorks32u.acgvideo.com/upgcxcode/86/56/98055686/98055686-1-32.flv?deadline=1462165219&gen=playurl&nbs=1&oi=1879473321&os=ks3u&platform=pc&trid=80a358d94bc442babc00f32db8ced2e5&uipk=5&upsig=988ad3ae4a680b41baccaafcf80bd2a8&uparams=deadline,gen,nbs,oi,os,platform,trid,uipk&mid=165584183&ksy_gslb_referer=https%3A%2F%2Fwww.bilibili.com%2Fvideo%2Fav14063582%2F%3Fspm_id_from%3D333.788.videocard.1"]}
{"cid": 99332008, "titleFormat": "\u7b2c25\u8bdd", "longTitle": "\u65bd\u4ec1\u5e03\u6cfd", "ep_id": 275629, "v_split_list": ["https://112-13-78-5.ksyungslb.com/upos-sz-mirrorks32u.acgvideo.com/upgcxcode/08/20/99332008/99332008-1-32.flv?deadline=1462165219&gen=playurl&nbs=1&oi=1879473321&os=ks3u&platform=pc&trid=80a358d94bc442babc00f32db8ced2e5&uipk=5&upsig=988ad3ae4a680b41baccaafcf80bd2a8&uparams=deadline,gen,nbs,oi,os,platform,trid,uipk&mid=165584183&ksy_gslb_referer=https%3A%2F%2Fwww.bilibili.com%2Fvideo%2Fav14063582%2F%3Fspm_id_from%3D333.788.videocard.1"]}
{"cid": 101145743, "titleFormat": "\u7b2c26\u8bdd", "longTitle": "\u6270\u6e05\u6c60\u9759", "ep_id": 275995, "v_split_list": ["https://112-13-78-5.ksyungslb.com/upos-sz-mirrorks32u.acgvideo.com/upgcxcode/43/57/101145743/101145743-1-32.flv?deadline=1462165219&gen=playurl&nbs=1&oi=1879473321&os=ks3u&platform=pc&trid=80a358d94bc442babc00f32db8ced2e5&uipk=5&upsig=988ad3ae4a680b41baccaafcf80bd2a8&uparams=deadline,gen,nbs,oi,os,platform,trid,uipk&mid=165584183&ksy_gslb_referer=https%3A%2F%2Fwww.bilibili.com%2Fvideo%2Fav14063582%2F%3Fspm_id_from%3D333.788.videocard.1"]}
